jupyterlite_pyodide_lock_webdriver/__init__.py
jupyterlite_pyodide_lock_webdriver/browsers.py
jupyterlite_pyodide_lock_webdriver/locker.py
jupyterlite_pyodide_lock_webdriver/py.typed
jupyterlite_pyodide_lock_webdriver-0.1.1.dist-info/entry_points.txt
jupyterlite_pyodide_lock_webdriver-0.1.1.dist-info/LICENSE
jupyterlite_pyodide_lock_webdriver-0.1.1.dist-info/WHEEL
jupyterlite_pyodide_lock_webdriver-0.1.1.dist-info/METADATA
jupyterlite_pyodide_lock_webdriver-0.1.1.dist-info/RECORD
