Metadata-Version: 2.3
Name: jupyterlite-pyodide-lock-webdriver
Version: 0.1.1
Summary: A WebDriver strategy for jupyterlite-pyodide-lock
Author: jupyterlite-pyodide-lock contributors
Requires-Python: >=3.10
Classifier: Framework :: Jupyter
Classifier: Framework :: Jupyter :: JupyterLab
Classifier: Framework :: Jupyter :: JupyterLab :: 4
Classifier: License :: OSI Approved :: BSD License
Classifier: Programming Language :: Python
Classifier: Programming Language :: Python :: 3
Classifier: Programming Language :: Python :: 3.10
Classifier: Programming Language :: Python :: 3.11
Classifier: Programming Language :: Python :: 3.12
Classifier: Programming Language :: Python :: 3.13
Classifier: Typing :: Typed
Requires-Dist: jupyterlite-pyodide-lock ==0.1.1
Requires-Dist: selenium >=4.19
Requires-Dist: pytest >=8,<9 ; extra == "test"
Requires-Dist: pytest-cov ; extra == "test"
Requires-Dist: pytest-html ; extra == "test"
Project-URL: Bug Tracker, https://github.com/deathbeds/jupyterlite-pyodide-lock/issues
Project-URL: Changelog, https://github.com/deathbeds/jupyterlite-pyodide-lock/blob/main/CHANGELOG.md
Project-URL: Documentation, https://jupyterlite-pyodide-lock.rtfd.org
Project-URL: PyPI, https://pypi.org/project/jupyterlite-pyodide-lock
Project-URL: Source, https://github.com/deathbeds/jupyterlite-pyodide-lock/tree/main
Provides-Extra: test
